doop/__init__.py
doop/coe_plot.py
doop/constants.py
doop/elements.py
doop/hohmann.py
doop/objects.py
doop/smad.py
doop/tle.py
doop-0.1.0.dist-info/LICENSE
doop-0.1.0.dist-info/WHEEL
doop-0.1.0.dist-info/METADATA
doop-0.1.0.dist-info/RECORD
